movefilestd/__init__.py
movefilestd/mover.py
movefilestd-0.0.2.dist-info/LICENSE
movefilestd-0.0.2.dist-info/METADATA
movefilestd-0.0.2.dist-info/WHEEL
movefilestd-0.0.2.dist-info/top_level.txt
movefilestd-0.0.2.dist-info/RECORD
