Metadata-Version: 2.1
Name: movefilestd
Version: 0.0.2
Summary: task_1 from gnanendra
Home-page: https://github.com/singha111subhajit/movefilestd.git
Author: Subhajit
Author-email: singha111subhajit@gmail.com
License: UNKNOWN
Keywords: python
Platform: UNKNOWN
Classifier: Development Status :: 1 - Planning
Classifier: Intended Audience :: Developers
Classifier: Programming Language :: Python :: 3
Classifier: Operating System :: Unix
Classifier: Operating System :: MacOS :: MacOS X
Classifier: Operating System :: Microsoft :: Windows
License-File: LICENSE
